liststrops/__init__.py
liststrops/index.py
liststrops-0.0.3.dist-info/METADATA
liststrops-0.0.3.dist-info/WHEEL
liststrops-0.0.3.dist-info/top_level.txt
liststrops-0.0.3.dist-info/RECORD
