Metadata-Version: 2.1
Name: liststrops
Version: 0.0.3
Summary: My first package!
Author: JD6
